{
  "match_info": {
    "home_team": "PAOK",
    "away_team": "PANATHINAIKOS A.O.",
    "datetime": "26 April 2026 - 18:30"
  },
  "teams_comparison": {
    "titles": [
      {
        "raw": "Efficiency*",
        "spans": [
          "Efficiency*"
        ]
      },
      {
        "raw": "Perfect*",
        "spans": [
          "Perfect*"
        ]
      },
      {
        "raw": "Spikes per Set   (Played Set)",
        "spans": [
          "Spikes per Set",
          "(Played Set)"
        ]
      },
      {
        "raw": "Blocks per Set   (Played Set)",
        "spans": [
          "Blocks per Set",
          "(Played Set)"
        ]
      },
      {
        "raw": "Aces Scored",
        "spans": [
          "Aces Scored"
        ]
      },
      {
        "raw": "Aces per Set   (Played Set)",
        "spans": [
          "Aces per Set",
          "(Played Set)"
        ]
      },
      {
        "raw": "Perfect*",
        "spans": [
          "Perfect*"
        ]
      }
    ],
    "spikes": {
      "efficiency": {
        "home": "32%",
        "average": "33%",
        "away": "39%"
      },
      "spikes_per_set_home": "12.22",
      "spikes_per_set_avg": "11.97",
      "spikes_per_set_away": "12.49",
      "spikes_per_set_home_played": "(99)",
      "spikes_per_set_away_played": "(98)"
    },
    "blocks": {
      "blocks_per_set_home": "1.98",
      "blocks_per_set_avg": "2.07",
      "blocks_per_set_away": "2.03",
      "blocks_home_played": "(99)",
      "blocks_away_played": "(98)"
    },
    "serve": {
      "aces_home": "136",
      "aces_away": "246",
      "aces_per_set_home": "1.37",
      "aces_per_set_avg": "1.60",
      "aces_per_set_away": "2.51",
      "aces_home_played": "(99)",
      "aces_away_played": "(98)"
    },
    "reception": {
      "reception_eff_home": "39%",
      "reception_eff_avg": "35%",
      "reception_eff_away": "42%",
      "reception_perfect_home": "27%",
      "reception_perfect_avg": "25%",
      "reception_perfect_away": "25%"
    }
  }
}