[
  {
    "team": "ΑΟΝΣ ΜΙΛΩΝ",
    "points": 19,
    "matches": 7
  },
  {
    "team": "ΠΑΝΑΘΗΝΑΪΚΟΣ AO",
    "points": 16,
    "matches": 7
  },
  {
    "team": "ΠΑΟΚ",
    "points": 13,
    "matches": 7
  },
  {
    "team": "ΟΦΗ",
    "points": 12,
    "matches": 7
  },
  {
    "team": "ΟΛΥΜΠΙΑΚΟΣ ΣΦΠ OΝΕΧ",
    "points": 11,
    "matches": 6
  },
  {
    "team": "ΑΟ ΚΑΛΑΜΑΤΑ 80 AFFIDEA",
    "points": 9,
    "matches": 6
  },
  {
    "team": "ΑΟ ΦΟΙΝΙΚΑΣ ΣΥΡΟΥ",
    "points": 6,
    "matches": 6
  },
  {
    "team": "ΠΑΝΙΩΝΙΟΣ",
    "points": 4,
    "matches": 6
  },
  {
    "team": "ΑΟΠ ΚΗΦΙΣΙΑΣ",
    "points": 3,
    "matches": 6
  },
  {
    "team": "ΑΟ ΦΛΟΙΣΒΟΣ MEMBERS PARON",
    "points": 3,
    "matches": 6
  }
]