{
  "games": [
    {
      "homeTeam": "ΜΙΛΩΝ",
      "homeSlug": "milon",
      "awayTeam": "ΠΑΟΚ",
      "awaySlug": "paok",
      "refs": {
        "referees": [
          "Μυλωνάκης",
          "Πρέντζας"
        ],
        "observer": "Μαυρικίδης",
        "challengeRef": "Κουτσούλας",
        "linesmen": [
          "Τομαράς",
          "Τουκτούκας"
        ],
        "secretariat": "Θεοδωρίδου"
      }
    },
    {
      "homeTeam": "ΠΑΝΑΘΗΝΑΪΚΟΣ",
      "homeSlug": "panathinaikos",
      "awayTeam": "ΟΛΥΜΠΙΑΚΟΣ",
      "awaySlug": "olympiakos",
      "refs": {
        "referees": [
          "Νικάκης",
          "Γεωργιάδης"
        ],
        "observer": "Καλπακτσόγλου",
        "challengeRef": "Μουλά Λ.",
        "linesmen": [
          "Γεώργας",
          "Μουζακίτη"
        ],
        "secretariat": "Καρατζογλίδου"
      }
    },
    {
      "homeTeam": "ΚΑΛΑΜΑΤΑ",
      "homeSlug": "kalamata",
      "awayTeam": "ΠΑΝΙΩΝΙΟΣ",
      "awaySlug": "panionios",
      "refs": {
        "referees": [
          "Φραγκάκης",
          "Καραγιαννόπουλος"
        ],
        "observer": "Ράπτης",
        "challengeRef": "",
        "linesmen": [
          "Βλάσσης",
          "Κοσμάς"
        ],
        "secretariat": "Ραβάνη"
      }
    }
  ]
}